data_grid/__init__.py
data_grid/register.py
data_grid/frontend/dist/index.html
data_grid/frontend/dist/vite.svg
data_grid/frontend/dist/assets/html2canvas.esm-7570f311-59a6f546.js
data_grid/frontend/dist/assets/index-d081bea5.css
data_grid/frontend/dist/assets/index-fb979fdb.js
data_grid/frontend/dist/assets/index.es-a25a1651-394cf16d.js
data_grid/frontend/dist/assets/purify.es-958e7803-b3d8833e.js
bp_data_grid-1.0.8.dist-info/LICENSE
bp_data_grid-1.0.8.dist-info/METADATA
bp_data_grid-1.0.8.dist-info/WHEEL
bp_data_grid-1.0.8.dist-info/top_level.txt
bp_data_grid-1.0.8.dist-info/RECORD
