Metadata-Version: 2.1
Name: bp-data-grid
Version: 1.0.8
Summary: Show data in data grid
Home-page: UNKNOWN
Author: Bluepineapple
Author-email: avinash@bluepineapple.io
License: UNKNOWN
Platform: UNKNOWN
Requires-Python: >=3.8.10
Requires-Dist: streamlit (>=1.20.0)
